CHANGES.txt
MANIFEST.in
README.rst
docs_requirements.txt
setup.py
tests_requirements.txt
loggers/__init__.py
loggers/loggers.py
loggers.egg-info/PKG-INFO
loggers.egg-info/SOURCES.txt
loggers.egg-info/dependency_links.txt
loggers.egg-info/not-zip-safe
loggers.egg-info/top_level.txt