Metadata-Version: 1.1
Name: loggers
Version: 0.1.3
Summary: Usefull wrapper methods for logging native package
Home-page: https://github.com/jonDel/loggers
Author: jonDel
Author-email: jdellagostin@gmail.com
License: GPLv3
Platform: UNKNOWN
Classifier: Development Status :: 3 - Alpha
Classifier: License :: OSI Approved :: GNU General Public License v3 (GPLv3)
Classifier: Programming Language :: Python :: 2.6
Classifier: Programming Language :: Python :: 2.7
Classifier: Topic :: System :: Logging
